{
  "_class": "shapePath",
  "booleanOperation": -1,
  "clippingMaskMode": 0,
  "do_objectID": "A3342205-5B20-4742-ADA6-DADA158DBE56",
  "edited": true,
  "exportOptions": {
    "_class": "exportOptions",
    "exportFormats": [
    ],
    "includedLayerIds": [
    ],
    "layerOptions": 0,
    "shouldTrim": false
  },
  "frame": {
    "_class": "rect",
    "constrainProportions": false,
    "height": 55.60000000000014,
    "width": 44.00000000000023,
    "x": 0,
    "y": 0
  },
  "hasClippingMask": false,
  "isClosed": true,
  "isFixedToViewport": false,
  "isFlippedHorizontal": false,
  "isFlippedVertical": false,
  "isLocked": false,
  "isVisible": true,
  "layerListExpandedType": 0,
  "name": "Path",
  "nameIsFixed": false,
  "pointRadiusBehaviour": 1,
  "points": [
    {
      "_class": "curvePoint",
      "cornerRadius": 0,
      "curveFrom": "{0.91818181818181033, 0.12230215827338223}",
      "curveMode": 2,
      "curveTo": "{0.75454545454544653, 0.025179856115109488}",
      "hasCurveFrom": true,
      "hasCurveTo": true,
      "point": "{0.83636363636363098, 0.073741007194244826}"
    },
    {
      "_class": "curvePoint",
      "cornerRadius": 0,
      "curveFrom": "{0.95909090909090522, 0.32374100719424381}",
      "curveMode": 3,
      "curveTo": "{0.95909090909090522, 0.1888489208633089}",
      "hasCurveFrom": true,
      "hasCurveTo": true,
      "point": "{0.95909090909090522, 0.27338129496402891}"
    },
    {
      "_class": "curvePoint",
      "cornerRadius": 0,
      "curveFrom": "{0.87272727272727024, 0.4388489208633099}",
      "curveMode": 2,
      "curveTo": "{0.94090909090908814, 0.3669064748201446}",
      "hasCurveFrom": true,
      "hasCurveTo": true,
      "point": "{0.90681818181817919, 0.40287769784172728}"
    },
    {
      "_class": "curvePoint",
      "cornerRadius": 0,
      "curveFrom": "{0.76363636363636278, 0.48561151079136777}",
      "curveMode": 4,
      "curveTo": "{0.82499999999999984, 0.46762589928057646}",
      "hasCurveFrom": false,
      "hasCurveTo": true,
      "point": "{0.76363636363636278, 0.48561151079136777}"
    },
    {
      "_class": "curvePoint",
      "cornerRadius": 0,
      "curveFrom": "{0.8386363636363614, 0.50719424460431817}",
      "curveMode": 4,
      "curveTo": "{0.76363636363636278, 0.48741007194244729}",
      "hasCurveFrom": true,
      "hasCurveTo": false,
      "point": "{0.76363636363636278, 0.48741007194244729}"
    },
    {
      "_class": "curvePoint",
      "cornerRadius": 0,
      "curveFrom": "{0.97954545454545261, 0.6169064748201456}",
      "curveMode": 2,
      "curveTo": "{0.89772727272727326, 0.53776978417266219}",
      "hasCurveFrom": true,
      "hasCurveTo": true,
      "point": "{0.93863636363636294, 0.57733812949640395}"
    },
    {
      "_class": "curvePoint",
      "cornerRadius": 0,
      "curveFrom": "{1, 0.81115107913669116}",
      "curveMode": 3,
      "curveTo": "{1, 0.66726618705036056}",
      "hasCurveFrom": true,
      "hasCurveTo": true,
      "point": "{1, 0.72661870503597104}"
    },
    {
      "_class": "curvePoint",
      "cornerRadius": 0,
      "curveFrom": "{0.77727272727272434, 0.97482014388489258}",
      "curveMode": 2,
      "curveTo": "{0.95454545454545481, 0.8776978417266178}",
      "hasCurveFrom": true,
      "hasCurveTo": true,
      "point": "{0.86590909090908952, 0.92625899280575519}"
    },
    {
      "_class": "curvePoint",
      "cornerRadius": 0,
      "curveFrom": "{0.34318181818181953, 1}",
      "curveMode": 2,
      "curveTo": "{0.65454545454545532, 1}",
      "hasCurveFrom": true,
      "hasCurveTo": true,
      "point": "{0.49772727272727224, 1}"
    },
    {
      "_class": "curvePoint",
      "cornerRadius": 0,
      "curveFrom": "{0.04545454545454522, 0.8776978417266178}",
      "curveMode": 2,
      "curveTo": "{0.22272727272727572, 0.97482014388489258}",
      "hasCurveFrom": true,
      "hasCurveTo": true,
      "point": "{0.13409090909091045, 0.92625899280575519}"
    },
    {
      "_class": "curvePoint",
      "cornerRadius": 0,
      "curveFrom": "{0, 0.66726618705036056}",
      "curveMode": 3,
      "curveTo": "{0, 0.81115107913669116}",
      "hasCurveFrom": true,
      "hasCurveTo": true,
      "point": "{0, 0.72661870503597104}"
    },
    {
      "_class": "curvePoint",
      "cornerRadius": 0,
      "curveFrom": "{0.10227272727272674, 0.53776978417266219}",
      "curveMode": 4,
      "curveTo": "{0.020454545454547415, 0.61870503597122317}",
      "hasCurveFrom": true,
      "hasCurveTo": true,
      "point": "{0.061363636363637078, 0.57733812949640395}"
    },
    {
      "_class": "curvePoint",
      "cornerRadius": 0,
      "curveFrom": "{0.23636363636363722, 0.48741007194244729}",
      "curveMode": 4,
      "curveTo": "{0.15909090909090826, 0.50719424460431817}",
      "hasCurveFrom": false,
      "hasCurveTo": true,
      "point": "{0.23636363636363722, 0.48741007194244729}"
    },
    {
      "_class": "curvePoint",
      "cornerRadius": 0,
      "curveFrom": "{0.17500000000000013, 0.46762589928057646}",
      "curveMode": 4,
      "curveTo": "{0.23636363636363722, 0.48561151079136777}",
      "hasCurveFrom": true,
      "hasCurveTo": false,
      "point": "{0.23636363636363722, 0.48561151079136777}"
    },
    {
      "_class": "curvePoint",
      "cornerRadius": 0,
      "curveFrom": "{0.059090909090911886, 0.3669064748201446}",
      "curveMode": 2,
      "curveTo": "{0.1272727272727297, 0.4388489208633099}",
      "hasCurveFrom": true,
      "hasCurveTo": true,
      "point": "{0.093181818181820794, 0.40287769784172728}"
    },
    {
      "_class": "curvePoint",
      "cornerRadius": 0,
      "curveFrom": "{0.040909090909094829, 0.1888489208633089}",
      "curveMode": 3,
      "curveTo": "{0.040909090909094829, 0.3219424460431663}",
      "hasCurveFrom": true,
      "hasCurveTo": true,
      "point": "{0.040909090909094829, 0.27338129496402891}"
    },
    {
      "_class": "curvePoint",
      "cornerRadius": 0,
      "curveFrom": "{0.24545454545454831, 0.025179856115107441}",
      "curveMode": 2,
      "curveTo": "{0.081818181818184496, 0.12230215827338223}",
      "hasCurveFrom": true,
      "hasCurveTo": true,
      "point": "{0.16363636363636899, 0.073741007194244826}"
    },
    {
      "_class": "curvePoint",
      "cornerRadius": 0,
      "curveFrom": "{0.64090909090908343, 2.0447272971513626e-15}",
      "curveMode": 4,
      "curveTo": "{0.35909090909091135, 0}",
      "hasCurveFrom": true,
      "hasCurveTo": true,
      "point": "{0.50000000000000255, 0}"
    }
  ],
  "resizingConstraint": 63,
  "resizingType": 0,
  "rotation": 0,
  "shouldBreakMaskChain": false,
  "style": {
    "_class": "style",
    "blur": {
      "_class": "blur",
      "center": "{0.5, 0.5}",
      "isEnabled": false,
      "motionAngle": 0,
      "radius": 10,
      "saturation": 1,
      "type": 0
    },
    "borderOptions": {
      "_class": "borderOptions",
      "dashPattern": [
      ],
      "isEnabled": true,
      "lineCapStyle": 0,
      "lineJoinStyle": 0
    },
    "borders": [
    ],
    "colorControls": {
      "_class": "colorControls",
      "brightness": 0,
      "contrast": 1,
      "hue": 0,
      "isEnabled": false,
      "saturation": 1
    },
    "contextSettings": {
      "_class": "graphicsContextSettings",
      "blendMode": 0,
      "opacity": 1
    },
    "do_objectID": "B435005F-CF67-4877-B22F-33B5B52BAAD2",
    "endMarkerType": 0,
    "fills": [
    ],
    "innerShadows": [
    ],
    "miterLimit": 10,
    "shadows": [
    ],
    "startMarkerType": 0,
    "windingRule": 1
  }
}