{
  "_class": "shapePath",
  "booleanOperation": -1,
  "clippingMaskMode": 0,
  "do_objectID": "940A3432-29E1-4237-A423-AC730C172523",
  "edited": true,
  "exportOptions": {
    "_class": "exportOptions",
    "exportFormats": [
    ],
    "includedLayerIds": [
    ],
    "layerOptions": 0,
    "shouldTrim": false
  },
  "frame": {
    "_class": "rect",
    "constrainProportions": false,
    "height": 111.551,
    "width": 175.713,
    "x": 414.239,
    "y": 908.869
  },
  "hasClippingMask": false,
  "isClosed": false,
  "isFixedToViewport": false,
  "isFlippedHorizontal": false,
  "isFlippedVertical": false,
  "isLocked": false,
  "isVisible": true,
  "layerListExpandedType": 0,
  "name": "Fill 21",
  "nameIsFixed": false,
  "pointRadiusBehaviour": 1,
  "points": [
    {
      "_class": "curvePoint",
      "cornerRadius": 0,
      "curveFrom": "{0.82003039046627202, 0.27001999085620015}",
      "curveMode": 4,
      "curveTo": "{0.84344926101085271, 0.39860691522263342}",
      "hasCurveFrom": true,
      "hasCurveTo": false,
      "point": "{0.84344926101085271, 0.39860691522263342}"
    },
    {
      "_class": "curvePoint",
      "cornerRadius": 0,
      "curveFrom": "{0.64551285334608122, 0.17582988946759759}",
      "curveMode": 3,
      "curveTo": "{0.7449761827525565, 0.17582988946759759}",
      "hasCurveFrom": true,
      "hasCurveTo": true,
      "point": "{0.6558137417265657, 0.17582988946759759}"
    },
    {
      "_class": "curvePoint",
      "cornerRadius": 0,
      "curveFrom": "{0.60033122193577038, 0.07481779634427306}",
      "curveMode": 4,
      "curveTo": "{0.63547375549902374, 0.17745246568833953}",
      "hasCurveFrom": true,
      "hasCurveTo": true,
      "point": "{0.625611081707102, 0.17987288325519218}"
    },
    {
      "_class": "curvePoint",
      "cornerRadius": 0,
      "curveFrom": "{0.36520348522875373, 0}",
      "curveMode": 3,
      "curveTo": "{0.53601611719110154, 0}",
      "hasCurveFrom": true,
      "hasCurveTo": true,
      "point": "{0.46046109280474412, 0}"
    },
    {
      "_class": "curvePoint",
      "cornerRadius": 0,
      "curveFrom": "{0.26610438612965454, 0.2602576400032271}",
      "curveMode": 4,
      "curveTo": "{0.28775901612288218, 0.11879767998493922}",
      "hasCurveFrom": true,
      "hasCurveTo": true,
      "point": "{0.28407118426069772, 0.26742924760871656}"
    },
    {
      "_class": "curvePoint",
      "cornerRadius": 0,
      "curveFrom": "{0.10203570595231985, 0.25642082993429005}",
      "curveMode": 3,
      "curveTo": "{0.24728961431425112, 0.25642082993429005}",
      "hasCurveFrom": true,
      "hasCurveTo": true,
      "point": "{0.22791142374212481, 0.25642082993429005}"
    },
    {
      "_class": "curvePoint",
      "cornerRadius": 0,
      "curveFrom": "{0, 0.81369059891887996}",
      "curveMode": 2,
      "curveTo": "{0, 0.41714552088282458}",
      "hasCurveFrom": true,
      "hasCurveTo": true,
      "point": "{0, 0.61541357764609894}"
    },
    {
      "_class": "curvePoint",
      "cornerRadius": 0,
      "curveFrom": "{0.25489292198072971, 0.97436150281037359}",
      "curveMode": 3,
      "curveTo": "{0.10203570595231985, 0.97436150281037359}",
      "hasCurveFrom": true,
      "hasCurveTo": true,
      "point": "{0.22791142374212481, 0.97436150281037359}"
    },
    {
      "_class": "curvePoint",
      "cornerRadius": 0,
      "curveFrom": "{0.31487140962820059, 0.96647273444433479}",
      "curveMode": 4,
      "curveTo": "{0.28078742039575882, 0.96692095991967797}",
      "hasCurveFrom": true,
      "hasCurveTo": true,
      "point": "{0.30481523848548492, 0.95338455056431548}"
    },
    {
      "_class": "curvePoint",
      "cornerRadius": 0,
      "curveFrom": "{0.35814652302333916, 0.97436150281037359}",
      "curveMode": 2,
      "curveTo": "{0.32777882114584567, 0.97436150281037359}",
      "hasCurveFrom": true,
      "hasCurveTo": true,
      "point": "{0.34185859896535814, 0.97436150281037359}"
    },
    {
      "_class": "curvePoint",
      "cornerRadius": 0,
      "curveFrom": "{0.41428921024625387, 0.98036772417997153}",
      "curveMode": 4,
      "curveTo": "{0.37284663058510165, 0.96387302668734454}",
      "hasCurveFrom": true,
      "hasCurveTo": true,
      "point": "{0.38340361840045978, 0.94684045862430632}"
    },
    {
      "_class": "curvePoint",
      "cornerRadius": 0,
      "curveFrom": "{0.53575432665767453, 1}",
      "curveMode": 2,
      "curveTo": "{0.45167403663929229, 1}",
      "hasCurveFrom": true,
      "hasCurveTo": true,
      "point": "{0.49200116098410468, 1}"
    },
    {
      "_class": "curvePoint",
      "cornerRadius": 0,
      "curveFrom": "{0.62587287224052834, 0.95634283870158043}",
      "curveMode": 4,
      "curveTo": "{0.57595055573577381, 0.97669227528215774}",
      "hasCurveFrom": true,
      "hasCurveTo": true,
      "point": "{0.60822477562843935, 0.93787594911744399}"
    },
    {
      "_class": "curvePoint",
      "cornerRadius": 0,
      "curveFrom": "{0.69391564653725091, 0.96710025010981504}",
      "curveMode": 2,
      "curveTo": "{0.64701530336400825, 0.96710025010981504}",
      "hasCurveFrom": true,
      "hasCurveTo": true,
      "point": "{0.66976831537791759, 0.96710025010981504}"
    },
    {
      "_class": "curvePoint",
      "cornerRadius": 0,
      "curveFrom": "{0.75963076152589737, 0.9551774524656883}",
      "curveMode": 4,
      "curveTo": "{0.71620767956838716, 0.9549085171804822}",
      "hasCurveFrom": true,
      "hasCurveTo": true,
      "point": "{0.73446472372562066, 0.93437979040976726}"
    },
    {
      "_class": "curvePoint",
      "cornerRadius": 0,
      "curveFrom": "{0.91878802365220569, 0.96710025010981504}",
      "curveMode": 3,
      "curveTo": "{0.788217149556379, 0.96710025010981504}",
      "hasCurveFrom": true,
      "hasCurveTo": true,
      "point": "{0.81860192472953042, 0.96710025010981504}"
    },
    {
      "_class": "curvePoint",
      "cornerRadius": 0,
      "curveFrom": "{1, 0.53685758083746404}",
      "curveMode": 3,
      "curveTo": "{1, 0.83917669944688977}",
      "hasCurveFrom": true,
      "hasCurveTo": true,
      "point": "{1, 0.68135650957857818}"
    },
    {
      "_class": "curvePoint",
      "cornerRadius": 0,
      "curveFrom": "{0.84344926101085271, 0.39860691522263342}",
      "curveMode": 4,
      "curveTo": "{0.93184909483077505, 0.41773717851027775}",
      "hasCurveFrom": false,
      "hasCurveTo": true,
      "point": "{0.84344926101085271, 0.39860691522263342}"
    }
  ],
  "resizingConstraint": 63,
  "resizingType": 0,
  "rotation": 0,
  "shouldBreakMaskChain": false,
  "style": {
    "_class": "style",
    "blur": {
      "_class": "blur",
      "center": "{0.5, 0.5}",
      "isEnabled": false,
      "motionAngle": 0,
      "radius": 10,
      "saturation": 1,
      "type": 0
    },
    "borderOptions": {
      "_class": "borderOptions",
      "dashPattern": [
      ],
      "isEnabled": true,
      "lineCapStyle": 0,
      "lineJoinStyle": 0
    },
    "borders": [
    ],
    "colorControls": {
      "_class": "colorControls",
      "brightness": 0,
      "contrast": 1,
      "hue": 0,
      "isEnabled": false,
      "saturation": 1
    },
    "contextSettings": {
      "_class": "graphicsContextSettings",
      "blendMode": 0,
      "opacity": 1
    },
    "do_objectID": "B44F7DF8-C3BB-4D0C-B48F-0E1E5F7E8A75",
    "endMarkerType": 0,
    "fills": [
      {
        "_class": "fill",
        "color": {
          "_class": "color",
          "alpha": 1,
          "blue": 0.9961473345756531,
          "green": 0.9987195134162903,
          "red": 1
        },
        "contextSettings": {
          "_class": "graphicsContextSettings",
          "blendMode": 0,
          "opacity": 1
        },
        "fillType": 0,
        "gradient": {
          "_class": "gradient",
          "elipseLength": 0,
          "from": "{0.5, 0}",
          "gradientType": 0,
          "stops": [
            {
              "_class": "gradientStop",
              "color": {
                "_class": "color",
                "alpha": 1,
                "blue": 1,
                "green": 1,
                "red": 1
              },
              "position": 0
            },
            {
              "_class": "gradientStop",
              "color": {
                "_class": "color",
                "alpha": 1,
                "blue": 0,
                "green": 0,
                "red": 0
              },
              "position": 1
            }
          ],
          "to": "{0.5, 1}"
        },
        "isEnabled": true,
        "noiseIndex": 0,
        "noiseIntensity": 0,
        "patternFillType": 1,
        "patternTileScale": 1
      }
    ],
    "innerShadows": [
    ],
    "miterLimit": 10,
    "shadows": [
    ],
    "startMarkerType": 0,
    "windingRule": 1
  }
}